mdformat_yamlfmt/__init__.py
mdformat_yamlfmt/py.typed
mdformat_yamlfmt-0.0.1.dist-info/METADATA
mdformat_yamlfmt-0.0.1.dist-info/WHEEL
mdformat_yamlfmt-0.0.1.dist-info/entry_points.txt
mdformat_yamlfmt-0.0.1.dist-info/licenses/LICENSE
mdformat_yamlfmt-0.0.1.dist-info/RECORD
