Metadata-Version: 2.4
Name: mdformat-yamlfmt
Version: 0.0.1
Summary: Mdformat plugin to format yaml code blocks using yamlfmt.
Author-email: Bagard Hoel <hoel.bagard.hy@hitachi-hightech.com>
License-File: LICENSE
Requires-Python: >=3.7
Requires-Dist: ruff
